nmwifi/__init__.py
nmwifi/_cli.py
nmwifi/_data.py
nmwifi/_nm_wrapper.py
nmwifi/actions.py
nmwifi/balance.py
nmwifi/checks.py
nmwifi/exceptions.py
nmwifi/setup.py
nmwifi-0.0.3.dist-info/METADATA
nmwifi-0.0.3.dist-info/WHEEL
nmwifi-0.0.3.dist-info/entry_points.txt
nmwifi-0.0.3.dist-info/RECORD
